README.txt
setup.py
collective/__init__.py
collective.geo.polymaps.egg-info/PKG-INFO
collective.geo.polymaps.egg-info/SOURCES.txt
collective.geo.polymaps.egg-info/dependency_links.txt
collective.geo.polymaps.egg-info/entry_points.txt
collective.geo.polymaps.egg-info/namespace_packages.txt
collective.geo.polymaps.egg-info/not-zip-safe
collective.geo.polymaps.egg-info/requires.txt
collective.geo.polymaps.egg-info/top_level.txt
collective/geo/__init__.py
collective/geo/polymaps/__init__.py
collective/geo/polymaps/configure.zcml
collective/geo/polymaps/interfaces.py
collective/geo/polymaps/setuphandlers.py
collective/geo/polymaps/tests.py
collective/geo/polymaps/version.txt
collective/geo/polymaps/browser/__init__.py
collective/geo/polymaps/browser/configure.zcml
collective/geo/polymaps/browser/mapview.py
collective/geo/polymaps/browser/utils.py
collective/geo/polymaps/browser/viewlets.py
collective/geo/polymaps/browser/templates/contentviewlet.pt
collective/geo/polymaps/browser/templates/jsviewlet.pt
collective/geo/polymaps/browser/templates/mapview.pt
collective/geo/polymaps/profiles/default/browserlayer.xml
collective/geo/polymaps/profiles/default/collecive.geo.polymaps_various.txt
collective/geo/polymaps/profiles/default/cssregistry.xml
collective/geo/polymaps/profiles/default/jsregistry.xml
collective/geo/polymaps/profiles/default/metadata.xml
collective/geo/polymaps/profiles/default/skins.xml
collective/geo/polymaps/profiles/default/types/Folder.xml
collective/geo/polymaps/profiles/default/types/Topic.xml
collective/geo/polymaps/skins/cg_polymaps_js/collective.geo.polymaps.js
collective/geo/polymaps/skins/cg_polymaps_js/polymaps.js
collective/geo/polymaps/skins/cg_polymaps_js/polymaps.min.js
collective/geo/polymaps/skins/cg_polymaps_styles/cg_polymaps.css
docs/HISTORY.txt
docs/INSTALL.txt
docs/LICENSE.GPL
docs/LICENSE.txt