Metadata-Version: 1.0
Name: collective.geo.polymaps
Version: 0.1
Summary: Collective Geo Polymaps integation
Home-page: http://plone.org/products/collective.geo.polymaps/
Author: UNKNOWN
Author-email: UNKNOWN
License: GPL
Platform: UNKNOWN
Classifier: Framework :: Plone
Classifier: Programming Language :: Python
Classifier: Framework :: Plone
Classifier: Framework :: Plone :: 4.0
Classifier: Framework :: Plone :: 4.1
Classifier: Intended Audience :: Developers
Classifier: License :: OSI Approved :: GNU General Public License (GPL)
Classifier: Topic :: Scientific/Engineering :: GIS
Classifier: Development Status :: 4 - Beta
